{
	"info": {
		"_postman_id": "9f510875-a553-4e18-bb01-d8cb2fcde358",
		"name": "digital-wallet",
		"schema": "https://schema.getpostman.com/json/collection/v2.1.0/collection.json",
		"_exporter_id": "33895269"
	},
	"item": [
		{
			"name": "registration",
			"request": {
				"method": "POST",
				"header": [
					{
						"key": "app",
						"value": "",
						"type": "text"
					},
					{
						"key": "Content-Type",
						"value": "application/json",
						"type": "text"
					}
				],
				"body": {
					"mode": "raw",
					"raw": "{\r\n    \"name\":\"agent\",\r\n    \"email\":\"agent@gmail.com\",\r\n    \"phone\":\"01925365523\",\r\n    \"password\":\"Roji@1234\"\r\n     \r\n    \r\n}"
				},
				"url": {
					"raw": "http://localhost:5000/api/v1/user/register",
					"protocol": "http",
					"host": [
						"localhost"
					],
					"port": "5000",
					"path": [
						"api",
						"v1",
						"user",
						"register"
					]
				}
			},
			"response": []
		},
		{
			"name": "user-login",
			"request": {
				"method": "GET",
				"header": []
			},
			"response": []
		},
		{
			"name": "admin-login",
			"request": {
				"method": "GET",
				"header": []
			},
			"response": []
		},
		{
			"name": "agent-login",
			"request": {
				"method": "GET",
				"header": []
			},
			"response": []
		},
		{
			"name": "update-user",
			"request": {
				"method": "GET",
				"header": []
			},
			"response": []
		},
		{
			"name": "add-money",
			"request": {
				"method": "GET",
				"header": []
			},
			"response": []
		},
		{
			"name": "withdraw-money",
			"request": {
				"method": "GET",
				"header": []
			},
			"response": []
		},
		{
			"name": "send-money",
			"request": {
				"method": "GET",
				"header": []
			},
			"response": []
		},
		{
			"name": "get-all-users",
			"request": {
				"method": "GET",
				"header": []
			},
			"response": []
		},
		{
			"name": "cash-out",
			"request": {
				"method": "GET",
				"header": []
			},
			"response": []
		},
		{
			"name": "get-all-agents",
			"request": {
				"method": "GET",
				"header": []
			},
			"response": []
		},
		{
			"name": "cash-in",
			"request": {
				"method": "GET",
				"header": []
			},
			"response": []
		},
		{
			"name": "transaction-history",
			"request": {
				"method": "GET",
				"header": []
			},
			"response": []
		},
		{
			"name": "create-transaction-peremeter",
			"request": {
				"method": "GET",
				"header": []
			},
			"response": []
		},
		{
			"name": "get all wallet",
			"request": {
				"method": "GET",
				"header": []
			},
			"response": []
		},
		{
			"name": "get all transaction",
			"request": {
				"method": "GET",
				"header": []
			},
			"response": []
		},
		{
			"name": "block wallet",
			"request": {
				"method": "GET",
				"header": []
			},
			"response": []
		},
		{
			"name": "unblock wallet",
			"request": {
				"method": "GET",
				"header": []
			},
			"response": []
		},
		{
			"name": "become-agent",
			"request": {
				"method": "GET",
				"header": []
			},
			"response": []
		},
		{
			"name": "handle agent request",
			"request": {
				"method": "GET",
				"header": []
			},
			"response": []
		}
	]
}